{
   "designHeight" : 800,
   "designWeight" : 400,
   "name" : null,
   "version" : 1,
   "widgetTree" : {
      "children" : [
         {
            "children" : [],
            "name" : "BUTTON_JX",
            "options" : {
               "color" : "255,255,255",
               "disabled" : "",
               "effect" : "",
               "flipX" : false,
               "flipY" : false,
               "font" : "普通",
               "fontName" : "msyh.ttf",
               "fontSize" : 16,
               "group" : 0,
               "height" : 62,
               "image" : "common/button_zt_1.png",
               "lbxoffset" : 0,
               "lbyoffset" : 0,
               "name" : "BUTTON_JX",
               "normal" : "common/button_zt_1.png",
               "opacity" : 100,
               "pressed" : "common/lbutton_zt_1.png",
               "rotation" : 0,
               "scale9" : false,
               "text" : "",
               "visible" : true,
               "width" : 151,
               "x" : 240,
               "y" : 518,
               "zorder" : 0
            },
            "type" : "Button"
         },
         {
            "children" : [],
            "name" : "BUTTON_END",
            "options" : {
               "color" : "255,255,255",
               "disabled" : "",
               "effect" : "",
               "flipX" : false,
               "flipY" : false,
               "font" : "普通",
               "fontName" : "msyh.ttf",
               "fontSize" : 16,
               "group" : 0,
               "height" : 62,
               "image" : "common/button_zt_1.png",
               "lbxoffset" : 0,
               "lbyoffset" : 0,
               "name" : "BUTTON_END",
               "normal" : "common/button_zt_1.png",
               "opacity" : 100,
               "pressed" : "common/lbutton_zt_1.png",
               "rotation" : 0,
               "scale9" : false,
               "text" : "",
               "visible" : true,
               "width" : 151,
               "x" : 240,
               "y" : 428,
               "zorder" : 0
            },
            "type" : "Button"
         },
         {
            "children" : [],
            "name" : "BUTTON_SHOP",
            "options" : {
               "color" : "255,255,255",
               "disabled" : "",
               "effect" : "",
               "flipX" : false,
               "flipY" : false,
               "font" : "普通",
               "fontName" : "msyh.ttf",
               "fontSize" : 16,
               "group" : 0,
               "height" : 62,
               "image" : "common/button_zt_2.png",
               "lbxoffset" : 0,
               "lbyoffset" : 0,
               "name" : "BUTTON_SHOP",
               "normal" : "common/button_zt_2.png",
               "opacity" : 100,
               "pressed" : "common/lbutton_zt_2.png",
               "rotation" : 0,
               "scale9" : false,
               "text" : "",
               "visible" : true,
               "width" : 151,
               "x" : 240,
               "y" : 338,
               "zorder" : 0
            },
            "type" : "Button"
         },
         {
            "children" : [],
            "name" : "ID_PICTURE_30332",
            "options" : {
               "flipX" : false,
               "flipY" : false,
               "font" : "普通",
               "group" : 0,
               "height" : 31,
               "image" : "common/zi_jxyx.png",
               "name" : "ID_PICTURE_30332",
               "opacity" : 100,
               "rotation" : 0,
               "scale9" : false,
               "visible" : true,
               "width" : 120,
               "x" : 240,
               "y" : 525,
               "zorder" : 0
            },
            "type" : "ImageView"
         },
         {
            "children" : [],
            "name" : "ID_PICTURE_30332",
            "options" : {
               "flipX" : false,
               "flipY" : false,
               "font" : "普通",
               "group" : 0,
               "height" : 31,
               "image" : "common/zi_tzzd.png",
               "name" : "ID_PICTURE_30332",
               "opacity" : 100,
               "rotation" : 0,
               "scale9" : false,
               "visible" : true,
               "width" : 121,
               "x" : 240,
               "y" : 435,
               "zorder" : 0
            },
            "type" : "ImageView"
         },
         {
            "children" : [],
            "name" : "PIC_SHOP",
            "options" : {
               "flipX" : false,
               "flipY" : false,
               "font" : "普通",
               "group" : 0,
               "height" : 31,
               "image" : "common/zi_shanc.png",
               "name" : "PIC_SHOP",
               "opacity" : 100,
               "rotation" : 0,
               "scale9" : false,
               "visible" : true,
               "width" : 74,
               "x" : 240,
               "y" : 345,
               "zorder" : 0
            },
            "type" : "ImageView"
         }
      ],
      "name" : "ID_FRAME_13496",
      "options" : {
         "flipX" : false,
         "flipY" : false,
         "font" : "普通",
         "group" : 0,
         "height" : 800,
         "image" : "",
         "name" : "ID_FRAME_13496",
         "opacity" : 100,
         "rotation" : 0,
         "scale9" : false,
         "visible" : true,
         "width" : 480,
         "x" : 240,
         "y" : 400,
         "zorder" : 0
      },
      "type" : "Panel"
   }
}
